rayen/__init__.py
rayen/constraint_module.py
rayen/constraints.py
rayen/utils.py
rayen-0.0.5.dist-info/LICENSE
rayen-0.0.5.dist-info/METADATA
rayen-0.0.5.dist-info/WHEEL
rayen-0.0.5.dist-info/top_level.txt
rayen-0.0.5.dist-info/RECORD
