Metadata-Version: 2.1
Name: rayen
Version: 0.0.5
Summary: Imposition of Hard Convex Constraints on Neural Networks
Author-email: Jesus Tordesillas <jtordesillas@ethz.ch>
License: BSD 3-Clause License
Project-URL: Homepage, https://github.com/leggedrobotics/rayen
Project-URL: Bug Tracker, https://github.com/leggedrobotics/rayen/issues
Classifier: Programming Language :: Python :: 3
Classifier: License :: OSI Approved :: BSD License
Classifier: Operating System :: OS Independent
Requires-Python: >=3.7
License-File: LICENSE
Requires-Dist: colorama (>=0.4.6)
Requires-Dist: cvxpy (>=1.3.1)
Requires-Dist: cvxpylayers (>=0.1.6)
Requires-Dist: numpy (>=1.24.2)
Requires-Dist: pycddlib (>=2.1.6)
Requires-Dist: scipy (>=1.10.1)
Requires-Dist: torch (>=1.13.1)
Requires-Dist: tqdm (>=4.65.0)
